tordirect/__init__.py
tordirect-0.0.0.dist-info/METADATA
tordirect-0.0.0.dist-info/WHEEL
tordirect-0.0.0.dist-info/top_level.txt
tordirect-0.0.0.dist-info/RECORD
