Metadata-Version: 2.1
Name: tordirect
Version: 0.0.0
Summary: In development
Author: baggedclangspoiling
